py_flat_orm/__about__.py
py_flat_orm/__init__.py
py_flat_orm/domain/__init__.py
py_flat_orm/domain/orm_actor.py
py_flat_orm/domain/orm_read.py
py_flat_orm/domain/orm_write.py
py_flat_orm/domain/py.typed
py_flat_orm/domain/conn/__init__.py
py_flat_orm/domain/conn/py.typed
py_flat_orm/domain/definition/__init__.py
py_flat_orm/domain/definition/abstract_orm_domain.py
py_flat_orm/domain/definition/orm_domain.py
py_flat_orm/domain/definition/orm_mapping.py
py_flat_orm/domain/definition/orm_validate.py
py_flat_orm/domain/definition/py.typed
py_flat_orm/domain/validation/__init__.py
py_flat_orm/domain/validation/orm_conditional_validate.py
py_flat_orm/domain/validation/orm_constraint.py
py_flat_orm/domain/validation/orm_constraint_type.py
py_flat_orm/domain/validation/orm_error_collector.py
py_flat_orm/domain/validation/orm_field_error.py
py_flat_orm/domain/validation/orm_field_errors.py
py_flat_orm/domain/validation/py.typed
py_flat_orm/domain_type/__init__.py
py_flat_orm/domain_type/py.typed
py_flat_orm/util/__init__.py
py_flat_orm/util/base_util/__init__.py
py_flat_orm/util/base_util/connection_util.py
py_flat_orm/util/base_util/domain_util.py
py_flat_orm/util/base_util/id_gen.py
py_flat_orm/util/base_util/in_fn.py
py_flat_orm/util/base_util/in_val.py
py_flat_orm/util/base_util/py.typed
py_flat_orm-0.2.0.dist-info/METADATA
py_flat_orm-0.2.0.dist-info/WHEEL
py_flat_orm-0.2.0.dist-info/licenses/LICENSE.txt
py_flat_orm-0.2.0.dist-info/RECORD
