Metadata-Version: 2.3
Name: py-flat-orm
Version: 0.2.0
Summary: A sample project for ORM
Project-URL: Documentation, https://github.com/ming.huang/py-flat-orm#readme
Project-URL: Issues, https://github.com/ming.huang/py-flat-orm/issues
Project-URL: Source, https://github.com/ming.huang/py-flat-orm
Author-email: "ming.huang" <means789@gmail.com>
License-Expression: MIT
License-File: LICENSE.txt
Classifier: Development Status :: 4 - Beta
Classifier: Programming Language :: Python
Classifier: Programming Language :: Python :: 3.8
Classifier: Programming Language :: Python :: 3.9
Classifier: Programming Language :: Python :: 3.10
Classifier: Programming Language :: Python :: 3.11
Classifier: Programming Language :: Python :: 3.12
Classifier: Programming Language :: Python :: Implementation :: CPython
Classifier: Programming Language :: Python :: Implementation :: PyPy
Requires-Python: >=3.8
Requires-Dist: numpy<2.0.0,>=1.21.0
Requires-Dist: pandas
Requires-Dist: pydash
Requires-Dist: pymysql
Requires-Dist: sqlalchemy
Provides-Extra: dev
Requires-Dist: black; extra == 'dev'
Requires-Dist: flake8; extra == 'dev'
Requires-Dist: mypy; extra == 'dev'
Requires-Dist: pylint; extra == 'dev'
